knit_openai/__init__.py
knit_openai/client/__init__.py
knit_openai/client/auth_client.py
knit_openai/client/http_client.py
knit_openai/client/sdk_client.py
knit_openai/exceptions/exceptions.py
knit_openai/logger.py
knit_openai/models/tools_filter.py
knit_openai/models/tools_summary.py
knit_openai/utils/constants.py
knit_openai-0.1.1.dist-info/METADATA
knit_openai-0.1.1.dist-info/WHEEL
knit_openai-0.1.1.dist-info/RECORD
