Metadata-Version: 2.3
Name: knit-openai
Version: 0.1.1
Summary: The Knit OpenAI SDK enables seamless integration between OpenAI-powered agents and SaaS applications. This toolkit allows developers to easily connect AI agents with hundreds of SaaS platforms using Knit's integration platform. With minimal code, expand your AI assistant's capabilities by incorporating external data and functionalities from popular business applications.
Author: Akshat
Author-email: akshat@getknit.dev
Requires-Python: >=3.9
Classifier: Programming Language :: Python :: 3
Classifier: Programming Language :: Python :: 3.9
Classifier: Programming Language :: Python :: 3.10
Classifier: Programming Language :: Python :: 3.11
Classifier: Programming Language :: Python :: 3.12
Classifier: Programming Language :: Python :: 3.13
Requires-Dist: httpx (>=0.28.1,<0.29.0)
Requires-Dist: openai (>=1.64.0,<2.0.0)
Requires-Dist: pydantic (>=2.10.6,<3.0.0)
